[
    {
        "Id": 1,
        "ShoeId": 1,
        "UserId": "d8f8889c-f73b-4d33-b663-5f5f130384bd",
        "Content": "obczajcie te najki",
        "DatePosted": "2024-11-09 15:50:42.8951861"
    },
    {
        "Id": 2,
        "ShoeId": 2,
        "UserId": "d8f8889c-f73b-4d33-b663-5f5f130384bd",
        "Content": "adidaski",
        "DatePosted": "2024-11-09 15:54:50.4005503"
    },
    {
        "Id": 3,
        "ShoeId": 4,
        "UserId": "d8f8889c-f73b-4d33-b663-5f5f130384bd",
        "Content": "dunki",
        "DatePosted": "2024-11-09 18:34:43.9323059"
    },
    {
        "Id": 4,
        "ShoeId": 5,
        "UserId": "96fbff26-302d-4656-bf40-60c7b5ba796c",
        "Content": "aaa",
        "DatePosted": "2024-11-14 17:30:27.4036897"
    },
    {
        "Id": 5,
        "ShoeId": 7,
        "UserId": "96fbff26-302d-4656-bf40-60c7b5ba796c",
        "Content": "aaaa",
        "DatePosted": "2024-11-14 17:30:31.8150098"
    },
    {
        "Id": 6,
        "ShoeId": 10,
        "UserId": "96fbff26-302d-4656-bf40-60c7b5ba796c",
        "Content": "aaaaa",
        "DatePosted": "2024-11-14 17:30:41.4654473"
    },
    {
        "Id": 7,
        "ShoeId": 11,
        "UserId": "96fbff26-302d-4656-bf40-60c7b5ba796c",
        "Content": "aaaaa",
        "DatePosted": "2024-11-14 17:30:50.9456831"
    },
    {
        "Id": 8,
        "ShoeId": 12,
        "UserId": "1ee60781-360c-46ca-bacf-d0eb4c36c25e",
        "Content": "bbb",
        "DatePosted": "2024-11-14 17:32:37.8670003"
    },
    {
        "Id": 9,
        "ShoeId": 13,
        "UserId": "1ee60781-360c-46ca-bacf-d0eb4c36c25e",
        "Content": "bbb",
        "DatePosted": "2024-11-14 17:32:43.3211004"
    },
    {
        "Id": 10,
        "ShoeId": 14,
        "UserId": "1ee60781-360c-46ca-bacf-d0eb4c36c25e",
        "Content": "bbb",
        "DatePosted": "2024-11-14 17:32:50.3766212"
    },
    {
        "Id": 11,
        "ShoeId": 15,
        "UserId": "29c193f9-2c38-4c0a-a5f4-77d4f15989d7",
        "Content": "ccc",
        "DatePosted": "2024-11-14 17:34:08.5570527"
    },
    {
        "Id": 12,
        "ShoeId": 16,
        "UserId": "29c193f9-2c38-4c0a-a5f4-77d4f15989d7",
        "Content": "ccc",
        "DatePosted": "2024-11-14 17:34:13.0667600"
    },
    {
        "Id": 13,
        "ShoeId": 17,
        "UserId": "29c193f9-2c38-4c0a-a5f4-77d4f15989d7",
        "Content": "ccc",
        "DatePosted": "2024-11-14 17:34:17.8365695"
    },
    {
        "Id": 14,
        "ShoeId": 19,
        "UserId": "e6c1db8e-59d9-4558-ad7f-12631a099cb2",
        "Content": "ddd",
        "DatePosted": "2024-11-14 17:35:16.3053353"
    },
    {
        "Id": 15,
        "ShoeId": 20,
        "UserId": "e6c1db8e-59d9-4558-ad7f-12631a099cb2",
        "Content": "ddd",
        "DatePosted": "2024-11-14 17:35:21.4589762"
    },
    {
        "Id": 16,
        "ShoeId": 21,
        "UserId": "9cc9379f-82af-4ddc-be60-cf68c25e4b79",
        "Content": "new",
        "DatePosted": "2024-11-14 17:38:16.4571516"
    },
    {
        "Id": 17,
        "ShoeId": 22,
        "UserId": "9cc9379f-82af-4ddc-be60-cf68c25e4b79",
        "Content": "new",
        "DatePosted": "2024-11-14 17:38:21.6462876"
    },
    {
        "Id": 18,
        "ShoeId": 23,
        "UserId": "9cc9379f-82af-4ddc-be60-cf68c25e4b79",
        "Content": "new",
        "DatePosted": "2024-11-14 17:38:28.6501273"
    },
    {
        "Id": 19,
        "ShoeId": 2,
        "UserId": "d8f8889c-f73b-4d33-b663-5f5f130384bd",
        "Content": "aaa\nbbb\nccc\nddd\neee",
        "DatePosted": "2024-11-16 09:41:51.4910957"
    },
    {
        "Id": 20,
        "ShoeId": 3,
        "UserId": "d8f8889c-f73b-4d33-b663-5f5f130384bd",
        "Content": "wdawsdawd",
        "DatePosted": "2024-11-16 10:27:09.3027233"
    },
    {
        "Id": 22,
        "ShoeId": 4,
        "UserId": "d8f8889c-f73b-4d33-b663-5f5f130384bd",
        "Content": "dwadadadwa\nfawfafwaf\nfawfaf\nfawfaf\nfwaffawfaffawffawfaffaffwafwa",
        "DatePosted": "2024-11-17 13:28:24.7450624"
    }
]